porto_test_package/__init__.py
porto_test_package/hello.py
porto_test_package-0.0.28.dist-info/METADATA
porto_test_package-0.0.28.dist-info/WHEEL
porto_test_package-0.0.28.dist-info/RECORD
