Metadata-Version: 2.3
Name: porto-test-package
Version: 0.0.28
Summary: Test 42 Porto package!
Author-email: Tisantos <olbrien@42lisboa.com>
Maintainer-email: Tisantos <olbrien@42lisboa.com>
Requires-Python: >=3.8
